tencentcloud/__init__.py
tencentcloud/facefusion/__init__.py
tencentcloud/facefusion/v20181201/__init__.py
tencentcloud/facefusion/v20181201/errorcodes.py
tencentcloud/facefusion/v20181201/facefusion_client.py
tencentcloud/facefusion/v20181201/models.py
tencentcloud/facefusion/v20220927/__init__.py
tencentcloud/facefusion/v20220927/errorcodes.py
tencentcloud/facefusion/v20220927/facefusion_client.py
tencentcloud/facefusion/v20220927/models.py
tencentcloud_sdk_python_facefusion-3.0.1482.dist-info/METADATA
tencentcloud_sdk_python_facefusion-3.0.1482.dist-info/WHEEL
tencentcloud_sdk_python_facefusion-3.0.1482.dist-info/top_level.txt
tencentcloud_sdk_python_facefusion-3.0.1482.dist-info/RECORD
